LICENSE
MANIFEST.in
Makefile
README.md
dev_requirements.txt
example.py
flask_idempotent2.py
requirements.txt
setup.py
flask_idempotent2.egg-info/PKG-INFO
flask_idempotent2.egg-info/SOURCES.txt
flask_idempotent2.egg-info/dependency_links.txt
flask_idempotent2.egg-info/not-zip-safe
flask_idempotent2.egg-info/requires.txt
flask_idempotent2.egg-info/top_level.txt
tests/.conftest.py.swp
tests/.fixtures.py.swp
tests/.test_idempotent.py.swp
tests/.test_keyfunc.py.swp
tests/__init__.py
tests/conftest.py
tests/fixtures.py
tests/test_idempotent.py
tests/test_keyfunc.py
tests/__pycache__/__init__.cpython-35.pyc
tests/__pycache__/conftest.cpython-35-PYTEST.pyc
tests/__pycache__/fixtures.cpython-35.pyc
tests/__pycache__/test_idempotent.cpython-35-PYTEST.pyc
tests/__pycache__/test_keyfunc.cpython-35-PYTEST.pyc