Metadata-Version: 1.1
Name: flask-idempotent2
Version: 0.0.6
Summary: Redis based idempotent support for sqlalchemy based flaskapplications.
Home-page: http://github.com/hit9/flask-docjson
Author: Chao Wang
Author-email: hit9@icloud.com
License: BSD
Platform: any
Classifier: Environment :: Web Environment
Classifier: Intended Audience :: Developers
Classifier: License :: OSI Approved :: BSD License
Classifier: Operating System :: OS Independent
Classifier: Programming Language :: Python :: 2.7
Classifier: Programming Language :: Python :: 3.3
Classifier: Programming Language :: Python :: 3.4
Classifier: Programming Language :: Python :: 3.5
Classifier: Topic :: Internet :: WWW/HTTP :: Dynamic Content
Classifier: Topic :: Software Development :: Libraries :: Python Modules
